multiindex/__init__.py
multiindex/index_property_verifier.py
multiindex/indexed_by.py
multiindex/multiindex.py
multiindex/view.py
multiindex-0.2.0.dist-info/METADATA
multiindex-0.2.0.dist-info/RECORD
multiindex-0.2.0.dist-info/WHEEL
multiindex-0.2.0.dist-info/top_level.txt
