Metadata-Version: 2.1
Name: multiindex
Version: 0.2.0
Summary: Container similar to boost multi index
Home-page: https://github.com/sushobhit27/multiindex
Author: Sushobhit
Author-email: sushobhitsolanki@gmail.com
License: UNKNOWN
Download-URL: https://github.com/sushobhit27/multiindex/archive/0.1.tar.gz
Keywords: container,multi index,boost
Platform: UNKNOWN
Classifier: Development Status :: 4 - Beta
Classifier: License :: OSI Approved :: MIT License
Classifier: Programming Language :: Python :: 2.7
Classifier: Programming Language :: Python :: 3
Classifier: Programming Language :: Python :: 3.6
Classifier: Programming Language :: Python :: Implementation :: CPython
Classifier: Operating System :: Microsoft
Classifier: Operating System :: Microsoft :: Windows :: Windows 7
Classifier: Operating System :: Unix
Classifier: Topic :: Software Development :: Libraries :: Python Modules
Classifier: Topic :: Utilities
Classifier: Intended Audience :: Developers
